rpi_stt_tts_shell/__init__.py
rpi_stt_tts_shell/main.py
rpi_stt_tts_shell-0.4.0.dist-info/LICENSE
rpi_stt_tts_shell-0.4.0.dist-info/METADATA
rpi_stt_tts_shell-0.4.0.dist-info/WHEEL
rpi_stt_tts_shell-0.4.0.dist-info/entry_points.txt
rpi_stt_tts_shell-0.4.0.dist-info/RECORD
